LICENCE
README.md
setup.py
fp23dpy/__calibrate_main__.py
fp23dpy/__init__.py
fp23dpy/__main__.py
fp23dpy/__segmentation_main__.py
fp23dpy/calibration.py
fp23dpy/demodulation.py
fp23dpy/export.py
fp23dpy/fp23dpy.py
fp23dpy/frequency_peak_finder.py
fp23dpy/helpers.py
fp23dpy/post_processing.py
fp23dpy/roi.py
fp23dpy/segmentation.py
fp23dpy/simulation.py
fp23dpy/version.py
fp23dpy/wavelets.py
fp23dpy.egg-info/PKG-INFO
fp23dpy.egg-info/SOURCES.txt
fp23dpy.egg-info/dependency_links.txt
fp23dpy.egg-info/entry_points.txt
fp23dpy.egg-info/requires.txt
fp23dpy.egg-info/top_level.txt
fp23dpy/examples/__init__.py
fp23dpy/examples/example_cone.py
fp23dpy/examples/example_cone_bump.py
fp23dpy/examples/example_cylinder.py
fp23dpy/examples/example_drop.py
fp23dpy/examples/example_plane.py