Metadata-Version: 2.1
Name: fp23dpy
Version: 0.3.34
Summary: Package for 3D reconstruction of Fringe Patterns captured using the Fringe Projection - Laser Induced Fluorescence technique.
Home-page: https://gitlab.com/roth.adrian/fp23dpy
Author: Adrian Roth
Author-email: adrian.roth@forbrf.lth.se
License: UNKNOWN
Platform: UNKNOWN
Classifier: Programming Language :: Python :: 3
Classifier: License :: OSI Approved :: MIT License
Classifier: Operating System :: OS Independent
Requires-Python: >=3.6
License-File: LICENCE
